flask_reverse_proxy_fix/__init__.py
flask_reverse_proxy_fix/middleware/__init__.py
flask_reverse_proxy_fix-0.2.1.dist-info/LICENSE.md
flask_reverse_proxy_fix-0.2.1.dist-info/METADATA
flask_reverse_proxy_fix-0.2.1.dist-info/WHEEL
flask_reverse_proxy_fix-0.2.1.dist-info/top_level.txt
flask_reverse_proxy_fix-0.2.1.dist-info/RECORD
