Metadata-Version: 2.1
Name: flask-reverse-proxy-fix
Version: 0.2.1
Summary: Python Flask middleware for applications running under a reverse proxy
Home-page: https://github.com/antarctica/flask-reverse-proxy-fix
Author: British Antarctic Survey
Author-email: webapps@bas.ac.uk
License: Open Government Licence v3.0
Platform: UNKNOWN
Classifier: Programming Language :: Python :: 3
Classifier: Framework :: Flask
Classifier: Development Status :: 5 - Production/Stable
Classifier: License :: Other/Proprietary License
Classifier: Operating System :: OS Independent
Classifier: Intended Audience :: Developers
Requires-Dist: flask
